{  "origem": "SISCOM",  "canal": "Canal Europa",  "competencia": "2020-11",  "idUnicoRP": "1876842",  "numeroRP": 233596,  "observacao": "TESTE123",  "statusRP": "ATIVO",  "estruturaComercial": {    "codigo": 240,    "nome": "Paralelas Globo Rj"  },  "agencia": {    "idUnico": "223176",    "id": "223176",    "nome": "ALMAP",    "mnemonico": "ALMAP",    "cnpjcpf": "62050174000116",    "nomeFantasia": "ALMAP",    "razaoSocial": "ALMAP BBDO PUBLICIDADE E COMUNICACOES LT"  },  "cliente": {    "idUnico": "10278",    "id": "10278",    "nome": "BRADESCO",    "mnemonico": "BRADESCO",    "cnpjcpf": "60746948001607",    "nomeFantasia": "BRADESCO AG ASSIS CENTRO EST UNIF",    "razaoSocial": "BANCO BRADESCO SA"  },  "items": [    {      "idItem": "1876842_5",      "mercado": "GN6",      "idLinha": 5,      "dataExibicao": "2020-11-02 12:00:00",      "modalidade": "CPT",      "duracao": 30,      "statusItem": "ATIVO",      "exibidoras": [        {          "idItem": 158172792,          "exibidora": "GN6"        }      ],      "programa": {        "id": 26907,        "mnemonico": "6N21H",        "nome": "6 NOVELA 21"      },      "material": {        "id": "2930652",        "codigo": 222163,        "titulo": "CGA TESTE LOC 0050"      },      "dataReserva": {        "inclusao": "2020-10-21 10:59:00",        "alteracao": "2020-10-21 11:00:00"      },      "break": {        "fixa": "null",        "posicaoSequencial": "null"      }    }  ]}